sodshock/__init__.py
sodshock/_version.py
sodshock-0.1.9.dist-info/LICENSE
sodshock-0.1.9.dist-info/METADATA
sodshock-0.1.9.dist-info/WHEEL
sodshock-0.1.9.dist-info/top_level.txt
sodshock-0.1.9.dist-info/RECORD
