Metadata-Version: 2.1
Name: sodshock
Version: 0.1.9
Summary: A package which numerically solves the sod shock tube problem
Home-page: https://github.com/ibackus/sod-shocktube
Author: Isaac Backus
License: UNKNOWN
Platform: UNKNOWN
Classifier: Programming Language :: Python
Classifier: Programming Language :: Python :: 2
Classifier: Programming Language :: Python :: 2.7
Classifier: Programming Language :: Python :: 3
License-File: LICENSE
Requires-Dist: numpy (>=1.3.0)
Requires-Dist: matplotlib (>=2.0.0)
Requires-Dist: scipy (>=1.0.0)
